{
  "editor:delete-paragraph": [],
  "editor:toggle-checklist-status": [],
  "editor:toggle-fold": [
    {
      "modifiers": [
        "Mod"
      ],
      "key": "/"
    }
  ],
  "editor:toggle-comments": [],
  "app:open-settings": [
    {
      "modifiers": [
        "Mod"
      ],
      "key": "O"
    }
  ],
  "tag-pane:open": [
    {
      "modifiers": [
        "Alt",
        "Shift"
      ],
      "key": "T"
    }
  ],
  "workspace:next-tab": [
    {
      "modifiers": [
        "Mod"
      ],
      "key": "PageDown"
    }
  ],
  "workspace:previous-tab": [
    {
      "modifiers": [
        "Mod"
      ],
      "key": "PageUp"
    }
  ],
  "file-explorer:reveal-active-file": [
    {
      "modifiers": [
        "Mod",
        "Shift"
      ],
      "key": "E"
    }
  ],
  "tab-shifter:focus-next-tab": [
    {
      "modifiers": [
        "Mod"
      ],
      "key": "Tab"
    }
  ],
  "tab-shifter:focus-prev-tab": [
    {
      "modifiers": [
        "Mod",
        "Shift"
      ],
      "key": "Tab"
    }
  ],
  "file-explorer:move-file": [
    {
      "modifiers": [
        "Mod"
      ],
      "key": "M"
    }
  ],
  "obsidian-quick-access:open-quick-access-1": [
    {
      "modifiers": [
        "Mod"
      ],
      "key": "1"
    }
  ],
  "workspace:goto-tab-1": [],
  "obsidian-quick-access:open-quick-access-2": [
    {
      "modifiers": [
        "Mod"
      ],
      "key": "2"
    }
  ],
  "obsidian-quick-access:open-quick-access-3": [
    {
      "modifiers": [
        "Mod"
      ],
      "key": "3"
    }
  ],
  "obsidian-quick-access:open-quick-access-4": [
    {
      "modifiers": [
        "Mod"
      ],
      "key": "4"
    }
  ],
  "workspace:goto-tab-2": [],
  "workspace:goto-tab-3": [],
  "workspace:goto-tab-4": [],
  "workspace:goto-tab-5": [],
  "workspace:goto-tab-6": [],
  "workspace:goto-tab-7": [],
  "workspace:goto-tab-8": [],
  "obsidian-quick-access:open-quick-access-5": [
    {
      "modifiers": [
        "Mod"
      ],
      "key": "0"
    }
  ],
  "obsidian-quick-access:open-quick-access-6": [
    {
      "modifiers": [
        "Mod"
      ],
      "key": "5"
    }
  ],
  "app:reload": [
    {
      "modifiers": [
        "Mod",
        "Shift"
      ],
      "key": "R"
    }
  ],
  "command-palette:open": [
    {
      "modifiers": [
        "Mod",
        "Shift"
      ],
      "key": "P"
    }
  ],
  "switcher:open": [
    {
      "modifiers": [
        "Mod"
      ],
      "key": "P"
    }
  ],
  "app:toggle-left-sidebar": [
    {
      "modifiers": [
        "Mod",
        "Shift"
      ],
      "key": "B"
    }
  ],
  "app:go-back": [
    {
      "modifiers": [
        "Alt"
      ],
      "key": "ArrowLeft"
    }
  ],
  "app:go-forward": [
    {
      "modifiers": [
        "Alt"
      ],
      "key": "ArrowRight"
    }
  ],
  "obsidian-editor-shortcuts:addCursorsToSelectionEnds": [],
  "obsidian-editor-shortcuts:copyLineDown": [],
  "obsidian-editor-shortcuts:copyLineUp": [],
  "editor:open-link-in-new-leaf": [],
  "editor:open-link-in-new-window": [
    {
      "modifiers": [
        "Alt",
        "Shift"
      ],
      "key": "Enter"
    }
  ],
  "editor:open-link-in-new-split": [],
  "editor:open-search-replace": [
    {
      "modifiers": [
        "Alt",
        "Mod"
      ],
      "key": "F"
    }
  ],
  "editor:toggle-highlight": [
    {
      "modifiers": [
        "Mod"
      ],
      "key": "H"
    }
  ],
  "obsidian-editor-shortcuts:duplicateLine": [],
  "obsidian-editor-shortcuts:selectAllOccurrences": [],
  "obsidian-editor-shortcuts:joinLines": [],
  "obsidian-editor-shortcuts:insertLineAbove": [],
  "obsidian-editor-shortcuts:insertLineBelow": [
    {
      "modifiers": [
        "Mod"
      ],
      "key": "Enter"
    }
  ],
  "obsidian-editor-shortcuts:insertCursorAbove": [
    {
      "modifiers": [
        "Alt",
        "Mod"
      ],
      "key": "ArrowUp"
    }
  ],
  "obsidian-editor-shortcuts:insertCursorBelow": [
    {
      "modifiers": [
        "Alt",
        "Mod"
      ],
      "key": "ArrowDown"
    }
  ],
  "editor:swap-line-up": [
    {
      "modifiers": [
        "Alt"
      ],
      "key": "ArrowUp"
    }
  ],
  "editor:swap-line-down": [
    {
      "modifiers": [
        "Alt"
      ],
      "key": "ArrowDown"
    }
  ]
}